maistro_s3_tool/__init__.py
maistro_s3_tool/tool.py
maistro_s3_tool-0.1.0.dist-info/licenses/LICENSE
maistro_s3_tool-0.1.0.dist-info/METADATA
maistro_s3_tool-0.1.0.dist-info/WHEEL
maistro_s3_tool-0.1.0.dist-info/top_level.txt
maistro_s3_tool-0.1.0.dist-info/RECORD
