Metadata-Version: 2.4
Name: maistro-s3-tool
Version: 0.1.0
Summary: AWS S3 üzerinde upload/download/list/presign işlemleri yapan Maistro uyumlu tool
Author-email: Mine Korkmaz <rminekorkmaz@gmail.com>
License: MIT
Requires-Python: >=3.9
License-File: LICENSE
Requires-Dist: boto3>=1.34
Requires-Dist: maistro-sdk>=1.6.0
Provides-Extra: dev
Requires-Dist: pytest>=7.4; extra == "dev"
Requires-Dist: moto[s3]>=5.0; extra == "dev"
Requires-Dist: build; extra == "dev"
Requires-Dist: twine; extra == "dev"
Dynamic: license-file
